get_cert.py
get_cert-19.1.2.dist-info/LICENSE
get_cert-19.1.2.dist-info/WHEEL
get_cert-19.1.2.dist-info/METADATA
get_cert-19.1.2.dist-info/RECORD
